pyeti/__init__.py
pyeti/api.py
pyeti/scripts/__init__.py
pyeti/scripts/addfiles.py
pyeti/scripts/cli.py
pyeti/scripts/getfile.py
tests/__init__.py
tests/test.py
tests/test_cli.py
tests/test_observables.py
pyeti_python3-1.0.dist-info/LICENSE.md
pyeti_python3-1.0.dist-info/METADATA
pyeti_python3-1.0.dist-info/WHEEL
pyeti_python3-1.0.dist-info/entry_points.txt
pyeti_python3-1.0.dist-info/top_level.txt
pyeti_python3-1.0.dist-info/RECORD
