Metadata-Version: 2.1
Name: pyeti-python3
Version: 1.0
Summary: Revival version of pyeti, the API for Yeti Threat Intel Platform.
Home-page: https://github.com/yeti-platform/pyeti
Author: Yeti core developers | packaged by Thomas Roccia @fr0gger_
License: Apache
Keywords: yeti threat intel api
Platform: UNKNOWN
Classifier: License :: OSI Approved :: Apache Software License
Classifier: Development Status :: 5 - Production/Stable
Classifier: Programming Language :: Python :: 3
Requires-Python: >=3.6
